<JavaCallout name='Java-CreateMultipartForm-1b' continueOnError='true'>
  <Properties>
    <Property name="debug">true</Property>
    <Property name="descriptor">
    {
      "hello" : {
        "content-var" :  "textFileData",
        "content-type" : "text/plain",
        "want-b64-decode": false
      }
    }
    </Property>
    <!--
    <Property name="destination">alternativeMessage</Property>
    -->
  </Properties>
  <ClassName>com.google.apigee.callouts.MultipartFormCreatorV2</ClassName>
  <ResourceURL>java://apigee-multipart-form-20230628.jar</ResourceURL>
</JavaCallout>
